chencrafts/__init__.py
chencrafts/py.typed
chencrafts/pyrightconfig.json
chencrafts/settings.py
chencrafts/version.py
chencrafts/bsqubits/__init__.py
chencrafts/bsqubits/batched_custom_sweeps.py
chencrafts/bsqubits/batched_sweeps_recipe.py
chencrafts/bsqubits/cat_ideal.py
chencrafts/bsqubits/cat_real.py
chencrafts/bsqubits/cat_recipe.py
chencrafts/bsqubits/cost_function.py
chencrafts/bsqubits/derive_var.py
chencrafts/bsqubits/error_budgeting.py
chencrafts/bsqubits/error_rates.py
chencrafts/bsqubits/pulse_utils.py
chencrafts/bsqubits/systems.py
chencrafts/bsqubits/QEC_graph/__init__.py
chencrafts/bsqubits/QEC_graph/cat_tree.py
chencrafts/bsqubits/QEC_graph/edge.py
chencrafts/bsqubits/QEC_graph/graph.py
chencrafts/bsqubits/QEC_graph/node.py
chencrafts/bsqubits/QEC_graph/settings.py
chencrafts/bsqubits/QEC_graph/utils.py
chencrafts/cqed/__init__.py
chencrafts/cqed/block_diag.py
chencrafts/cqed/clustered_me.py
chencrafts/cqed/crit_photon_num.py
chencrafts/cqed/decoherence.py
chencrafts/cqed/dq_helper.py
chencrafts/cqed/dynamics.py
chencrafts/cqed/flexible_sweep.py
chencrafts/cqed/floquet.py
chencrafts/cqed/mode_assignment.py
chencrafts/cqed/proc_repr.py
chencrafts/cqed/pulses.py
chencrafts/cqed/qt_helper.py
chencrafts/cqed/scq_helper.py
chencrafts/cqed/spec_poly_fit.py
chencrafts/cqed/special_states.py
chencrafts/cqed/symbolic_bosons.py
chencrafts/cqed/custom_sweeps/__init__.py
chencrafts/cqed/custom_sweeps/crit_photon_num.py
chencrafts/cqed/custom_sweeps/decoherence.py
chencrafts/cqed/custom_sweeps/general.py
chencrafts/cqed/custom_sweeps/utils.py
chencrafts/fluxonium/__init__.py
chencrafts/fluxonium/analyzer_frf.py
chencrafts/fluxonium/batched_sweep_fif.py
chencrafts/fluxonium/batched_sweep_frf.py
chencrafts/fluxonium/batched_sweep_readout.py
chencrafts/projects/__init__.py
chencrafts/projects/fluxonium_tunable_coupler.py
chencrafts/projects/protomon_disorder.py
chencrafts/projects/protomon_full_disorder.py
chencrafts/projects/reduce_readout_model.py
chencrafts-3.9.dist-info/licenses/LICENSE
chencrafts-3.9.dist-info/METADATA
chencrafts-3.9.dist-info/WHEEL
chencrafts-3.9.dist-info/top_level.txt
chencrafts-3.9.dist-info/RECORD
