Metadata-Version: 2.4
Name: chencrafts
Version: 3.9
Summary: A personal toolbox for superconducting qubits and quantum mechanics.
Author-email: Danyang Chen <DanyangChen2026@u.northwestern.edu>
License: BSD 3-Clause License
Project-URL: Homepage, https://github.com/Harrinive/chencrafts
Project-URL: Repository, https://github.com/Harrinive/chencrafts
Keywords: personal toolbox,superconducting qubits,quantum mechanics
Classifier: Development Status :: 4 - Beta
Classifier: Intended Audience :: Science/Research
Classifier: License :: OSI Approved :: BSD License
Classifier: Programming Language :: Python
Classifier: Programming Language :: Python :: 3
Classifier: Programming Language :: Python :: 3.10
Classifier: Topic :: Scientific/Engineering
Classifier: Operating System :: MacOS
Classifier: Operating System :: POSIX
Classifier: Operating System :: Unix
Classifier: Operating System :: Microsoft :: Windows
Requires-Python: >=3.10
License-File: LICENSE
Requires-Dist: numpy
Requires-Dist: matplotlib
Requires-Dist: scipy
Requires-Dist: pandas
Requires-Dist: tqdm
Requires-Dist: dill
Requires-Dist: pathos
Requires-Dist: scqubits>=3.0.0
Requires-Dist: IPython
Requires-Dist: h5py
Provides-Extra: cqed
Requires-Dist: torch>=1.7; extra == "cqed"
Requires-Dist: multiprocess; extra == "cqed"
Requires-Dist: pymablock; extra == "cqed"
Requires-Dist: jax; extra == "cqed"
Provides-Extra: fluxonium
Requires-Dist: jax; extra == "fluxonium"
Requires-Dist: qontrol; extra == "fluxonium"
Requires-Dist: dynamiqs; extra == "fluxonium"
Requires-Dist: optax; extra == "fluxonium"
Provides-Extra: bsqubits
Requires-Dist: networkx>=2.4; extra == "bsqubits"
Requires-Dist: cvxpy; extra == "bsqubits"
Dynamic: license-file
